XBXBOT/__init__.py
Mathyslol-1.1.7.dist-info/METADATA
Mathyslol-1.1.7.dist-info/WHEEL
Mathyslol-1.1.7.dist-info/top_level.txt
Mathyslol-1.1.7.dist-info/RECORD
