Metadata-Version: 2.1
Name: Mathyslol
Version: 1.1.7
Summary: The Best Fortnite LOBBYBOT with the latest features
Home-page: https://www.youtube.com
Author: Mathyslol
Classifier: Programming Language :: Python :: 3
Classifier: License :: OSI Approved :: MIT License
Classifier: Operating System :: OS Independent
Requires-Dist: crayons
Requires-Dist: fortnitepy ==3.6.9
Requires-Dist: BenBotAsync
Requires-Dist: FortniteAPIAsync
Requires-Dist: uvloop
Requires-Dist: sanic ==22.12.0
Requires-Dist: colorama
Requires-Dist: aiohttp
